{"cameraMode":{"drawMode":0,"name":"Shaded","section":"Shading Mode"},"sceneLighting":true,"audioPlay":false,"sceneViewState":{"m_AlwaysRefresh":false,"showFog":true,"showSkybox":true,"showFlares":true,"showImageEffects":true,"showParticleSystems":true,"showVisualEffectGraphs":true,"m_FxEnabled":true},"in2DMode":false,"pivot":{"x":3.101940155029297,"y":3.632495880126953,"z":-3.162764549255371},"rotation":{"x":-0.001903811702504754,"y":-0.6138342022895813,"z":0.0014775339514017106,"w":-0.7894434332847595},"size":5.5175065994262699,"orthographic":false}